hub2lab_hook-0.0.1.dist-info/DESCRIPTION.rst
hub2lab_hook-0.0.1.dist-info/METADATA
hub2lab_hook-0.0.1.dist-info/RECORD
hub2lab_hook-0.0.1.dist-info/WHEEL
hub2lab_hook-0.0.1.dist-info/metadata.json
hub2lab_hook-0.0.1.dist-info/top_level.txt
hub2labhook/__init__.py
