Metadata-Version: 2.0
Name: hub2lab-hook
Version: 0.0.1
Summary: hub2lab-hook
Home-page: https://github.com/ant31/hub2lab-hook
Author: Antoine Legrand
Author-email: 2t.antoine@gmail.com
License: Apache License version 2
Keywords: hub2lab-hook
Platform: UNKNOWN
Classifier: Development Status :: 2 - Pre-Alpha
Classifier: Intended Audience :: Developers
Classifier: Natural Language :: English
Classifier: Programming Language :: Python :: 2
Classifier: Programming Language :: Python :: 2.7
Requires-Dist: futures
